capsolver_async/__init__.py
capsolver_async/api_helper.py
capsolver_async/check.py
capsolver_async/exceptions.py
capsolver_async/pycapsolver.py
capsolver_async-0.1.dist-info/METADATA
capsolver_async-0.1.dist-info/WHEEL
capsolver_async-0.1.dist-info/top_level.txt
capsolver_async-0.1.dist-info/RECORD
